path/__init__.py
path/path.py
PyFAT12-0.8.dist-info/LICENSE
PyFAT12-0.8.dist-info/METADATA
PyFAT12-0.8.dist-info/WHEEL
PyFAT12-0.8.dist-info/top_level.txt
PyFAT12-0.8.dist-info/RECORD
