Metadata-Version: 2.1
Name: PyFAT12
Version: 0.8
Summary: A library for reading (from) and writing (to) FAT12 file systems
Home-page: https://github.com/hisahi/PyFAT12
Author: Sampo Hippeläinen (hisahi)
License: UNKNOWN
Project-URL: Bug Tracker, https://github.com/hisahi/PyFAT12/issues
Platform: UNKNOWN
Classifier: Programming Language :: Python :: 3
Classifier: License :: OSI Approved :: MIT License
Classifier: Operating System :: OS Independent
Requires-Python: >=3.5
License-File: LICENSE
